thinc_apple_ops/ops.cpython-310-darwin.so
thinc_apple_ops/ops.cpp
thinc_apple_ops/blas.pyx
thinc_apple_ops/__init__.py
thinc_apple_ops/blas.pxd
thinc_apple_ops/py.typed
thinc_apple_ops/blas.cpython-310-darwin.so
thinc_apple_ops/ops.pyx
thinc_apple_ops/tests/__init__.py
thinc_apple_ops/tests/test_gemm.py
thinc_apple_ops-1.0.0.dist-info/zip-safe
thinc_apple_ops-1.0.0.dist-info/RECORD
thinc_apple_ops-1.0.0.dist-info/LICENSE
thinc_apple_ops-1.0.0.dist-info/WHEEL
thinc_apple_ops-1.0.0.dist-info/entry_points.txt
thinc_apple_ops-1.0.0.dist-info/top_level.txt
thinc_apple_ops-1.0.0.dist-info/METADATA
